{"annotations": [{"original_image_path": "1001.png", "crop_coordinates": [], "width": 1328, "height": 1200, "image_path": "images/1001.png", "bbox_info": [{"box_coordinates": [179, 209, 233, 270], "box_attr": {"box_retain": 1, "box_age": 0}}]}, {"original_image_path": "1002.png", "crop_coordinates": [], "width": 1328, "height": 1200, "image_path": "images/1002.png", "bbox_info": [{"box_coordinates": [177, 226, 238, 291], "box_attr": {"box_retain": 1, "box_age": 0}}]}, {"original_image_path": "1003.png", "crop_coordinates": [], "width": 1328, "height": 1200, "image_path": "images/1003.png", "bbox_info": [{"box_coordinates": [176, 246, 238, 306], "box_attr": {"box_retain": 1, "box_age": 0}}]}, {"original_image_path": "1004.png", "crop_coordinates": [], "width": 1328, "height": 1200, "image_path": "images/1004.png", "bbox_info": [{"box_coordinates": [179, 252, 237, 315], "box_attr": {"box_retain": 1, "box_age": 0}}]}, {"original_image_path": "1005.png", "crop_coordinates": [], "width": 1328, "height": 1200, "image_path": "images/1005.png", "bbox_info": [{"box_coordinates": [179, 270, 241, 335], "box_attr": {"box_retain": 1, "box_age": 0}}]}, {"original_image_path": "1006.png", "crop_coordinates": [], "width": 1328, "height": 1200, "image_path": "images/1006.png", "bbox_info": [{"box_coordinates": [180, 295, 241, 358], "box_attr": {"box_retain": 1, "box_age": 0}}]}, {"original_image_path": "1007.png", "crop_coordinates": [], "width": 1328, "height": 1200, "image_path": "images/1007.png", "bbox_info": [{"box_coordinates": [178, 319, 240, 374], "box_attr": {"box_retain": 1, "box_age": 0}}]}, {"original_image_path": "1008.png", "crop_coordinates": [], "width": 1328, "height": 1200, "image_path": "images/1008.png", "bbox_info": [{"box_coordinates": [178, 322, 241, 381], "box_attr": {"box_retain": 1, "box_age": 0}}]}, {"original_image_path": "1009.png", "crop_coordinates": [], "width": 1328, "height": 1200, "image_path": "images/1009.png", "bbox_info": [{"box_coordinates": [179, 324, 241, 381], "box_attr": {"box_retain": 0, "box_age": 0}}, {"box_coordinates": [180, 363, 240, 418], "box_attr": {"box_retain": 1, "box_age": 0}}]}, {"original_image_path": "1010.png", "crop_coordinates": [], "width": 1328, "height": 1200, "image_path": "images/1010.png", "bbox_info": [{"box_coordinates": [180, 367, 241, 425], "box_attr": {"box_retain": 1, "box_age": 0}}]}, {"original_image_path": "1011.png", "crop_coordinates": [], "width": 1328, "height": 1200, "image_path": "images/1011.png", "bbox_info": [{"box_coordinates": [176, 388, 240, 446], "box_attr": {"box_retain": 1, "box_age": 0}}, {"box_coordinates": [198, 164, 250, 200], "box_attr": {"box_retain": 1, "box_age": 0}}]}, {"original_image_path": "1012.png", "crop_coordinates": [], "width": 1328, "height": 1200, "image_path": "images/1012.png", "bbox_info": [{"box_coordinates": [180, 411, 240, 467], "box_attr": {"box_retain": 1, "box_age": 0}}, {"box_coordinates": [198, 184, 250, 225], "box_attr": {"box_retain": 1, "box_age": 0}}]}, {"original_image_path": "1013.png", "crop_coordinates": [], "width": 1328, "height": 1200, "image_path": "images/1013.png", "bbox_info": [{"box_coordinates": [196, 203, 249, 246], "box_attr": {"box_retain": 1, "box_age": 0}}, {"box_coordinates": [181, 431, 241, 486], "box_attr": {"box_retain": 1, "box_age": 0}}]}, {"original_image_path": "1014.png", "crop_coordinates": [], "width": 1328, "height": 1200, "image_path": "images/1014.png", "bbox_info": [{"box_coordinates": [197, 222, 250, 270], "box_attr": {"box_retain": 1, "box_age": 0}}]}, {"original_image_path": "1015.png", "crop_coordinates": [], "width": 1328, "height": 1200, "image_path": "images/1015.png", "bbox_info": [{"box_coordinates": [201, 245, 249, 290], "box_attr": {"box_retain": 1, "box_age": 0}}]}, {"original_image_path": "1016.png", "crop_coordinates": [], "width": 1328, "height": 1200, "image_path": "images/1016.png", "bbox_info": [{"box_coordinates": [201, 263, 250, 310], "box_attr": {"box_retain": 1, "box_age": 0}}]}, {"original_image_path": "1017.png", "crop_coordinates": [], "width": 1328, "height": 1200, "image_path": "images/1017.png", "bbox_info": [{"box_coordinates": [200, 281, 248, 327], "box_attr": {"box_retain": 1, "box_age": 0}}]}, {"original_image_path": "1018.png", "crop_coordinates": [], "width": 1328, "height": 1200, "image_path": "images/1018.png", "bbox_info": [{"box_coordinates": [200, 283, 249, 333], "box_attr": {"box_retain": 1, "box_age": 0}}]}, {"original_image_path": "1019.png", "crop_coordinates": [], "width": 1328, "height": 1200, "image_path": "images/1019.png", "bbox_info": [{"box_coordinates": [200, 305, 249, 354], "box_attr": {"box_retain": 1, "box_age": 0}}]}, {"original_image_path": "1020.png", "crop_coordinates": [], "width": 1328, "height": 1200, "image_path": "images/1020.png", "bbox_info": [{"box_coordinates": [200, 327, 250, 375], "box_attr": {"box_retain": 1, "box_age": 0}}]}, {"original_image_path": "1021.png", "crop_coordinates": [], "width": 1328, "height": 1200, "image_path": "images/1021.png", "bbox_info": [{"box_coordinates": [201, 349, 249, 398], "box_attr": {"box_retain": 1, "box_age": 0}}]}, {"original_image_path": "1022.png", "crop_coordinates": [], "width": 1328, "height": 1200, "image_path": "images/1022.png", "bbox_info": [{"box_coordinates": [200, 366, 247, 412], "box_attr": {"box_retain": 1, "box_age": 0}}]}, {"original_image_path": "1023.png", "crop_coordinates": [], "width": 1328, "height": 1200, "image_path": "images/1023.png", "bbox_info": [{"box_coordinates": [198, 371, 249, 417], "box_attr": {"box_retain": 1, "box_age": 0}}]}, {"original_image_path": "1024.png", "crop_coordinates": [], "width": 1328, "height": 1200, "image_path": "images/1024.png", "bbox_info": [{"box_coordinates": [198, 393, 249, 438], "box_attr": {"box_retain": 1, "box_age": 0}}, {"box_coordinates": [190, 152, 267, 232], "box_attr": {"box_retain": 1, "box_age": 0}}]}, {"original_image_path": "1025.png", "crop_coordinates": [], "width": 1328, "height": 1200, "image_path": "images/1025.png", "bbox_info": [{"box_coordinates": [192, 172, 270, 251], "box_attr": {"box_retain": 1, "box_age": 0}}, {"box_coordinates": [196, 414, 250, 461], "box_attr": {"box_retain": 1, "box_age": 0}}]}, {"original_image_path": "1026.png", "crop_coordinates": [], "width": 1328, "height": 1200, "image_path": "images/1026.png", "bbox_info": [{"box_coordinates": [201, 431, 247, 481], "box_attr": {"box_retain": 1, "box_age": 0}}, {"box_coordinates": [194, 195, 271, 275], "box_attr": {"box_retain": 1, "box_age": 0}}]}, {"original_image_path": "1027.png", "crop_coordinates": [], "width": 1328, "height": 1200, "image_path": "images/1027.png", "bbox_info": [{"box_coordinates": [190, 219, 269, 294], "box_attr": {"box_retain": 1, "box_age": 0}}]}, {"original_image_path": "1028.png", "crop_coordinates": [], "width": 1328, "height": 1200, "image_path": "images/1028.png", "bbox_info": [{"box_coordinates": [193, 238, 270, 315], "box_attr": {"box_retain": 1, "box_age": 0}}]}, {"original_image_path": "1029.png", "crop_coordinates": [], "width": 1328, "height": 1200, "image_path": "images/1029.png", "bbox_info": [{"box_coordinates": [190, 252, 269, 332], "box_attr": {"box_retain": 1, "box_age": 0}}]}, {"original_image_path": "1030.png", "crop_coordinates": [], "width": 1328, "height": 1200, "image_path": "images/1030.png", "bbox_info": [{"box_coordinates": [192, 275, 269, 357], "box_attr": {"box_retain": 1, "box_age": 0}}]}, {"original_image_path": "1031.png", "crop_coordinates": [], "width": 1328, "height": 1200, "image_path": "images/1031.png", "bbox_info": [{"box_coordinates": [189, 283, 270, 363], "box_attr": {"box_retain": 1, "box_age": 0}}]}, {"original_image_path": "1032.png", "crop_coordinates": [], "width": 1328, "height": 1200, "image_path": "images/1032.png", "bbox_info": [{"box_coordinates": [191, 307, 272, 383], "box_attr": {"box_retain": 1, "box_age": 0}}]}, {"original_image_path": "1033.png", "crop_coordinates": [], "width": 1328, "height": 1200, "image_path": "images/1033.png", "bbox_info": [{"box_coordinates": [191, 326, 270, 405], "box_attr": {"box_retain": 1, "box_age": 0}}]}, {"original_image_path": "1034.png", "crop_coordinates": [], "width": 1328, "height": 1200, "image_path": "images/1034.png", "bbox_info": [{"box_coordinates": [192, 342, 271, 422], "box_attr": {"box_retain": 1, "box_age": 0}}]}, {"original_image_path": "1035.png", "crop_coordinates": [], "width": 1328, "height": 1200, "image_path": "images/1035.png", "bbox_info": [{"box_coordinates": [190, 365, 270, 451], "box_attr": {"box_retain": 1, "box_age": 0}}]}, {"original_image_path": "1036.png", "crop_coordinates": [], "width": 1328, "height": 1200, "image_path": "images/1036.png", "bbox_info": [{"box_coordinates": [191, 372, 270, 452], "box_attr": {"box_retain": 1, "box_age": 0}}]}, {"original_image_path": "1037.png", "crop_coordinates": [], "width": 1328, "height": 1200, "image_path": "images/1037.png", "bbox_info": [{"box_coordinates": [194, 394, 271, 473], "box_attr": {"box_retain": 1, "box_age": 0}}]}, {"original_image_path": "1038.png", "crop_coordinates": [], "width": 1328, "height": 1200, "image_path": "images/1038.png", "bbox_info": [{"box_coordinates": [201, 166, 276, 256], "box_attr": {"box_retain": 1, "box_age": 0}}]}, {"original_image_path": "1039.png", "crop_coordinates": [], "width": 1328, "height": 1200, "image_path": "images/1039.png", "bbox_info": [{"box_coordinates": [205, 190, 279, 276], "box_attr": {"box_retain": 1, "box_age": 0}}]}, {"original_image_path": "1040.png", "crop_coordinates": [], "width": 1328, "height": 1200, "image_path": "images/1040.png", "bbox_info": [{"box_coordinates": [205, 206, 281, 301], "box_attr": {"box_retain": 1, "box_age": 0}}]}, {"original_image_path": "1041.png", "crop_coordinates": [], "width": 1328, "height": 1200, "image_path": "images/1041.png", "bbox_info": [{"box_coordinates": [205, 211, 282, 302], "box_attr": {"box_retain": 1, "box_age": 0}}]}, {"original_image_path": "1042.png", "crop_coordinates": [], "width": 1328, "height": 1200, "image_path": "images/1042.png", "bbox_info": [{"box_coordinates": [210, 231, 286, 323], "box_attr": {"box_retain": 1, "box_age": 0}}]}, {"original_image_path": "1043.png", "crop_coordinates": [], "width": 1328, "height": 1200, "image_path": "images/1043.png", "bbox_info": [{"box_coordinates": [209, 254, 287, 352], "box_attr": {"box_retain": 1, "box_age": 0}}]}, {"original_image_path": "1044.png", "crop_coordinates": [], "width": 1328, "height": 1200, "image_path": "images/1044.png", "bbox_info": [{"box_coordinates": [211, 276, 287, 383], "box_attr": {"box_retain": 1, "box_age": 0}}]}, {"original_image_path": "1045.png", "crop_coordinates": [], "width": 1328, "height": 1200, "image_path": "images/1045.png", "bbox_info": [{"box_coordinates": [212, 298, 288, 402], "box_attr": {"box_retain": 1, "box_age": 0}}]}, {"original_image_path": "1046.png", "crop_coordinates": [], "width": 1328, "height": 1200, "image_path": "images/1046.png", "bbox_info": [{"box_coordinates": [214, 316, 289, 427], "box_attr": {"box_retain": 1, "box_age": 0}}]}, {"original_image_path": "1047.png", "crop_coordinates": [], "width": 1328, "height": 1200, "image_path": "images/1047.png", "bbox_info": [{"box_coordinates": [216, 332, 290, 444], "box_attr": {"box_retain": 1, "box_age": 0}}]}, {"original_image_path": "1048.png", "crop_coordinates": [], "width": 1328, "height": 1200, "image_path": "images/1048.png", "bbox_info": [{"box_coordinates": [214, 342, 290, 445], "box_attr": {"box_retain": 1, "box_age": 0}}]}, {"original_image_path": "1049.png", "crop_coordinates": [], "width": 1328, "height": 1200, "image_path": "images/1049.png", "bbox_info": [{"box_coordinates": [191, 158, 303, 235], "box_attr": {"box_retain": 1, "box_age": 0}}, {"box_coordinates": [214, 363, 292, 468], "box_attr": {"box_retain": 1, "box_age": 0}}]}, {"original_image_path": "1050.png", "crop_coordinates": [], "width": 1328, "height": 1200, "image_path": "images/1050.png", "bbox_info": [{"box_coordinates": [218, 382, 290, 486], "box_attr": {"box_retain": 1, "box_age": 0}}, {"box_coordinates": [189, 178, 301, 256], "box_attr": {"box_retain": 1, "box_age": 0}}]}, {"original_image_path": "1051.png", "crop_coordinates": [], "width": 1328, "height": 1200, "image_path": "images/1051.png", "bbox_info": [{"box_coordinates": [189, 195, 302, 276], "box_attr": {"box_retain": 1, "box_age": 0}}]}, {"original_image_path": "1052.png", "crop_coordinates": [], "width": 1328, "height": 1200, "image_path": "images/1052.png", "bbox_info": [{"box_coordinates": [191, 221, 302, 299], "box_attr": {"box_retain": 1, "box_age": 0}}]}, {"original_image_path": "1053.png", "crop_coordinates": [], "width": 1328, "height": 1200, "image_path": "images/1053.png", "bbox_info": [{"box_coordinates": [186, 239, 303, 317], "box_attr": {"box_retain": 1, "box_age": 0}}]}, {"original_image_path": "1054.png", "crop_coordinates": [], "width": 1328, "height": 1200, "image_path": "images/1054.png", "bbox_info": [{"box_coordinates": [189, 246, 300, 318], "box_attr": {"box_retain": 1, "box_age": 0}}]}, {"original_image_path": "1055.png", "crop_coordinates": [], "width": 1328, "height": 1200, "image_path": "images/1055.png", "bbox_info": [{"box_coordinates": [189, 269, 302, 343], "box_attr": {"box_retain": 1, "box_age": 0}}]}, {"original_image_path": "1056.png", "crop_coordinates": [], "width": 1328, "height": 1200, "image_path": "images/1056.png", "bbox_info": [{"box_coordinates": [189, 292, 301, 367], "box_attr": {"box_retain": 1, "box_age": 0}}]}, {"original_image_path": "1057.png", "crop_coordinates": [], "width": 1328, "height": 1200, "image_path": "images/1057.png", "bbox_info": [{"box_coordinates": [189, 310, 303, 381], "box_attr": {"box_retain": 1, "box_age": 0}}]}, {"original_image_path": "1058.png", "crop_coordinates": [], "width": 1328, "height": 1200, "image_path": "images/1058.png", "bbox_info": [{"box_coordinates": [185, 338, 298, 409], "box_attr": {"box_retain": 1, "box_age": 0}}]}, {"original_image_path": "1059.png", "crop_coordinates": [], "width": 1328, "height": 1200, "image_path": "images/1059.png", "bbox_info": [{"box_coordinates": [179, 357, 292, 424], "box_attr": {"box_retain": 1, "box_age": 0}}]}, {"original_image_path": "1060.png", "crop_coordinates": [], "width": 1328, "height": 1200, "image_path": "images/1060.png", "bbox_info": [{"box_coordinates": [178, 364, 290, 435], "box_attr": {"box_retain": 1, "box_age": 0}}]}, {"original_image_path": "1061.png", "crop_coordinates": [], "width": 1328, "height": 1200, "image_path": "images/1061.png", "bbox_info": [{"box_coordinates": [174, 386, 285, 457], "box_attr": {"box_retain": 1, "box_age": 0}}, {"box_coordinates": [185, 151, 280, 233], "box_attr": {"box_retain": 1, "box_age": 0}}]}, {"original_image_path": "1062.png", "crop_coordinates": [], "width": 1328, "height": 1200, "image_path": "images/1062.png", "bbox_info": [{"box_coordinates": [183, 172, 276, 282], "box_attr": {"box_retain": 1, "box_age": 0}}, {"box_coordinates": [176, 408, 289, 481], "box_attr": {"box_retain": 1, "box_age": 0}}]}, {"original_image_path": "1063.png", "crop_coordinates": [], "width": 1328, "height": 1200, "image_path": "images/1063.png", "bbox_info": [{"box_coordinates": [189, 194, 277, 291], "box_attr": {"box_retain": 1, "box_age": 0}}]}, {"original_image_path": "1064.png", "crop_coordinates": [], "width": 1328, "height": 1200, "image_path": "images/1064.png", "bbox_info": [{"box_coordinates": [183, 224, 278, 326], "box_attr": {"box_retain": 1, "box_age": 0}}]}, {"original_image_path": "1065.png", "crop_coordinates": [], "width": 1328, "height": 1200, "image_path": "images/1065.png", "bbox_info": [{"box_coordinates": [183, 242, 277, 349], "box_attr": {"box_retain": 1, "box_age": 0}}]}, {"original_image_path": "1066.png", "crop_coordinates": [], "width": 1328, "height": 1200, "image_path": "images/1066.png", "bbox_info": [{"box_coordinates": [186, 246, 275, 352], "box_attr": {"box_retain": 1, "box_age": 0}}]}, {"original_image_path": "1067.png", "crop_coordinates": [], "width": 1328, "height": 1200, "image_path": "images/1067.png", "bbox_info": [{"box_coordinates": [187, 268, 278, 369], "box_attr": {"box_retain": 1, "box_age": 0}}]}, {"original_image_path": "1068.png", "crop_coordinates": [], "width": 1328, "height": 1200, "image_path": "images/1068.png", "bbox_info": [{"box_coordinates": [185, 294, 278, 397], "box_attr": {"box_retain": 1, "box_age": 0}}]}, {"original_image_path": "1069.png", "crop_coordinates": [], "width": 1328, "height": 1200, "image_path": "images/1069.png", "bbox_info": [{"box_coordinates": [185, 310, 279, 419], "box_attr": {"box_retain": 1, "box_age": 0}}]}, {"original_image_path": "1070.png", "crop_coordinates": [], "width": 1328, "height": 1200, "image_path": "images/1070.png", "bbox_info": [{"box_coordinates": [188, 314, 280, 424], "box_attr": {"box_retain": 1, "box_age": 0}}]}, {"original_image_path": "1071.png", "crop_coordinates": [], "width": 1328, "height": 1200, "image_path": "images/1071.png", "bbox_info": [{"box_coordinates": [187, 339, 278, 443], "box_attr": {"box_retain": 1, "box_age": 0}}]}, {"original_image_path": "1072.png", "crop_coordinates": [], "width": 1328, "height": 1200, "image_path": "images/1072.png", "bbox_info": [{"box_coordinates": [182, 360, 278, 469], "box_attr": {"box_retain": 1, "box_age": 0}}, {"box_coordinates": [218, 150, 278, 213], "box_attr": {"box_retain": 1, "box_age": 0}}]}, {"original_image_path": "1073.png", "crop_coordinates": [], "width": 1328, "height": 1200, "image_path": "images/1073.png", "bbox_info": [{"box_coordinates": [219, 169, 279, 232], "box_attr": {"box_retain": 1, "box_age": 0}}, {"box_coordinates": [187, 384, 277, 487], "box_attr": {"box_retain": 1, "box_age": 0}}]}, {"original_image_path": "1074.png", "crop_coordinates": [], "width": 1328, "height": 1200, "image_path": "images/1074.png", "bbox_info": [{"box_coordinates": [220, 188, 277, 244], "box_attr": {"box_retain": 1, "box_age": 0}}]}, {"original_image_path": "1075.png", "crop_coordinates": [], "width": 1328, "height": 1200, "image_path": "images/1075.png", "bbox_info": [{"box_coordinates": [220, 190, 278, 246], "box_attr": {"box_retain": 1, "box_age": 0}}]}, {"original_image_path": "1076.png", "crop_coordinates": [], "width": 1328, "height": 1200, "image_path": "images/1076.png", "bbox_info": [{"box_coordinates": [218, 214, 276, 263], "box_attr": {"box_retain": 1, "box_age": 0}}]}, {"original_image_path": "1077.png", "crop_coordinates": [], "width": 1328, "height": 1200, "image_path": "images/1077.png", "bbox_info": [{"box_coordinates": [216, 237, 276, 291], "box_attr": {"box_retain": 1, "box_age": 0}}]}, {"original_image_path": "1078.png", "crop_coordinates": [], "width": 1328, "height": 1200, "image_path": "images/1078.png", "bbox_info": [{"box_coordinates": [218, 261, 276, 316], "box_attr": {"box_retain": 1, "box_age": 0}}]}, {"original_image_path": "1079.png", "crop_coordinates": [], "width": 1328, "height": 1200, "image_path": "images/1079.png", "bbox_info": [{"box_coordinates": [218, 275, 277, 329], "box_attr": {"box_retain": 1, "box_age": 0}}]}, {"original_image_path": "1080.png", "crop_coordinates": [], "width": 1328, "height": 1200, "image_path": "images/1080.png", "bbox_info": [{"box_coordinates": [216, 301, 274, 352], "box_attr": {"box_retain": 1, "box_age": 0}}]}, {"original_image_path": "1081.png", "crop_coordinates": [], "width": 1328, "height": 1200, "image_path": "images/1081.png", "bbox_info": [{"box_coordinates": [216, 306, 273, 358], "box_attr": {"box_retain": 1, "box_age": 0}}]}, {"original_image_path": "1082.png", "crop_coordinates": [], "width": 1328, "height": 1200, "image_path": "images/1082.png", "bbox_info": [{"box_coordinates": [214, 332, 274, 381], "box_attr": {"box_retain": 1, "box_age": 0}}]}, {"original_image_path": "1083.png", "crop_coordinates": [], "width": 1328, "height": 1200, "image_path": "images/1083.png", "bbox_info": [{"box_coordinates": [213, 360, 274, 402], "box_attr": {"box_retain": 1, "box_age": 0}}]}, {"original_image_path": "1084.png", "crop_coordinates": [], "width": 1328, "height": 1200, "image_path": "images/1084.png", "bbox_info": [{"box_coordinates": [218, 385, 275, 425], "box_attr": {"box_retain": 1, "box_age": 0}}]}, {"original_image_path": "1085.png", "crop_coordinates": [], "width": 1328, "height": 1200, "image_path": "images/1085.png", "bbox_info": [{"box_coordinates": [215, 400, 276, 443], "box_attr": {"box_retain": 1, "box_age": 0}}]}, {"original_image_path": "1086.png", "crop_coordinates": [], "width": 1328, "height": 1200, "image_path": "images/1086.png", "bbox_info": [{"box_coordinates": [203, 153, 283, 303], "box_attr": {"box_retain": 1, "box_age": 0}}, {"box_coordinates": [216, 424, 276, 462], "box_attr": {"box_retain": 1, "box_age": 0}}]}, {"original_image_path": "1087.png", "crop_coordinates": [], "width": 1328, "height": 1200, "image_path": "images/1087.png", "bbox_info": [{"box_coordinates": [203, 161, 282, 309], "box_attr": {"box_retain": 1, "box_age": 0}}, {"box_coordinates": [217, 413, 274, 467], "box_attr": {"box_retain": 1, "box_age": 0}}]}, {"original_image_path": "1088.png", "crop_coordinates": [], "width": 1328, "height": 1200, "image_path": "images/1088.png", "bbox_info": [{"box_coordinates": [200, 183, 283, 333], "box_attr": {"box_retain": 1, "box_age": 0}}, {"box_coordinates": [219, 436, 274, 488], "box_attr": {"box_retain": 1, "box_age": 0}}]}, {"original_image_path": "1089.png", "crop_coordinates": [], "width": 1328, "height": 1200, "image_path": "images/1089.png", "bbox_info": [{"box_coordinates": [203, 209, 283, 356], "box_attr": {"box_retain": 1, "box_age": 0}}]}, {"original_image_path": "1090.png", "crop_coordinates": [], "width": 1328, "height": 1200, "image_path": "images/1090.png", "bbox_info": [{"box_coordinates": [201, 232, 285, 381], "box_attr": {"box_retain": 1, "box_age": 0}}]}, {"original_image_path": "1091.png", "crop_coordinates": [], "width": 1328, "height": 1200, "image_path": "images/1091.png", "bbox_info": [{"box_coordinates": [204, 252, 285, 404], "box_attr": {"box_retain": 1, "box_age": 0}}]}, {"original_image_path": "1092.png", "crop_coordinates": [], "width": 1328, "height": 1200, "image_path": "images/1092.png", "bbox_info": [{"box_coordinates": [202, 270, 287, 420], "box_attr": {"box_retain": 1, "box_age": 0}}]}, {"original_image_path": "1093.png", "crop_coordinates": [], "width": 1328, "height": 1200, "image_path": "images/1093.png", "bbox_info": [{"box_coordinates": [201, 295, 285, 443], "box_attr": {"box_retain": 1, "box_age": 0}}]}, {"original_image_path": "1094.png", "crop_coordinates": [], "width": 1328, "height": 1200, "image_path": "images/1094.png", "bbox_info": [{"box_coordinates": [204, 300, 287, 451], "box_attr": {"box_retain": 1, "box_age": 0}}]}, {"original_image_path": "1095.png", "crop_coordinates": [], "width": 1328, "height": 1200, "image_path": "images/1095.png", "bbox_info": [{"box_coordinates": [204, 320, 286, 471], "box_attr": {"box_retain": 1, "box_age": 0}}]}, {"original_image_path": "1097.png", "crop_coordinates": [], "width": 1328, "height": 1200, "image_path": "images/1097.png", "bbox_info": [{"box_coordinates": [225, 169, 316, 247], "box_attr": {"box_retain": 1, "box_age": 0}}]}, {"original_image_path": "1098.png", "crop_coordinates": [], "width": 1328, "height": 1200, "image_path": "images/1098.png", "bbox_info": [{"box_coordinates": [225, 183, 304, 264], "box_attr": {"box_retain": 1, "box_age": 0}}]}, {"original_image_path": "1099.png", "crop_coordinates": [], "width": 1328, "height": 1200, "image_path": "images/1099.png", "bbox_info": [{"box_coordinates": [227, 209, 312, 288], "box_attr": {"box_retain": 1, "box_age": 0}}]}, {"original_image_path": "1100.png", "crop_coordinates": [], "width": 1328, "height": 1200, "image_path": "images/1100.png", "bbox_info": [{"box_coordinates": [227, 214, 311, 291], "box_attr": {"box_retain": 1, "box_age": 0}}]}, {"original_image_path": "1101.png", "crop_coordinates": [], "width": 1328, "height": 1200, "image_path": "images/1101.png", "bbox_info": [{"box_coordinates": [223, 235, 311, 315], "box_attr": {"box_retain": 1, "box_age": 0}}]}, {"original_image_path": "1102.png", "crop_coordinates": [], "width": 1328, "height": 1200, "image_path": "images/1102.png", "bbox_info": [{"box_coordinates": [227, 258, 310, 341], "box_attr": {"box_retain": 1, "box_age": 0}}]}, {"original_image_path": "1103.png", "crop_coordinates": [], "width": 1328, "height": 1200, "image_path": "images/1103.png", "bbox_info": [{"box_coordinates": [223, 285, 310, 363], "box_attr": {"box_retain": 1, "box_age": 0}}]}, {"original_image_path": "1104.png", "crop_coordinates": [], "width": 1328, "height": 1200, "image_path": "images/1104.png", "bbox_info": [{"box_coordinates": [226, 307, 309, 391], "box_attr": {"box_retain": 1, "box_age": 0}}]}, {"original_image_path": "1105.png", "crop_coordinates": [], "width": 1328, "height": 1200, "image_path": "images/1105.png", "bbox_info": [{"box_coordinates": [225, 324, 310, 406], "box_attr": {"box_retain": 1, "box_age": 0}}]}, {"original_image_path": "1106.png", "crop_coordinates": [], "width": 1328, "height": 1200, "image_path": "images/1106.png", "bbox_info": [{"box_coordinates": [227, 328, 310, 411], "box_attr": {"box_retain": 1, "box_age": 0}}]}, {"original_image_path": "1107.png", "crop_coordinates": [], "width": 1328, "height": 1200, "image_path": "images/1107.png", "bbox_info": [{"box_coordinates": [225, 350, 309, 436], "box_attr": {"box_retain": 1, "box_age": 0}}]}, {"original_image_path": "1108.png", "crop_coordinates": [], "width": 1328, "height": 1200, "image_path": "images/1108.png", "bbox_info": [{"box_coordinates": [227, 375, 310, 462], "box_attr": {"box_retain": 1, "box_age": 0}}]}, {"original_image_path": "1109.png", "crop_coordinates": [], "width": 1328, "height": 1200, "image_path": "images/1109.png", "bbox_info": [{"box_coordinates": [227, 393, 308, 479], "box_attr": {"box_retain": 1, "box_age": 0}}]}, {"original_image_path": "1112.png", "crop_coordinates": [], "width": 1328, "height": 1200, "image_path": "images/1112.png", "bbox_info": [{"box_coordinates": [203, 204, 345, 363], "box_attr": {"box_retain": 1, "box_age": 0}}]}, {"original_image_path": "1113.png", "crop_coordinates": [], "width": 1328, "height": 1200, "image_path": "images/1113.png", "bbox_info": [{"box_coordinates": [209, 227, 341, 387], "box_attr": {"box_retain": 1, "box_age": 0}}]}, {"original_image_path": "1114.png", "crop_coordinates": [], "width": 1328, "height": 1200, "image_path": "images/1114.png", "bbox_info": [{"box_coordinates": [210, 247, 350, 416], "box_attr": {"box_retain": 1, "box_age": 0}}]}, {"original_image_path": "1115.png", "crop_coordinates": [], "width": 1328, "height": 1200, "image_path": "images/1115.png", "bbox_info": [{"box_coordinates": [213, 266, 349, 430], "box_attr": {"box_retain": 1, "box_age": 0}}]}, {"original_image_path": "1116.png", "crop_coordinates": [], "width": 1328, "height": 1200, "image_path": "images/1116.png", "bbox_info": [{"box_coordinates": [218, 285, 353, 457], "box_attr": {"box_retain": 1, "box_age": 0}}]}, {"original_image_path": "1117.png", "crop_coordinates": [], "width": 1328, "height": 1200, "image_path": "images/1117.png", "bbox_info": [{"box_coordinates": [214, 290, 353, 465], "box_attr": {"box_retain": 1, "box_age": 0}}]}, {"original_image_path": "1118.png", "crop_coordinates": [], "width": 1328, "height": 1200, "image_path": "images/1118.png", "bbox_info": [{"box_coordinates": [215, 316, 349, 486], "box_attr": {"box_retain": 1, "box_age": 0}}]}, {"original_image_path": "1131.png", "crop_coordinates": [], "width": 1328, "height": 1200, "image_path": "images/1131.png", "bbox_info": [{"box_coordinates": [230, 185, 312, 244], "box_attr": {"box_retain": 1, "box_age": 0}}]}, {"original_image_path": "1132.png", "crop_coordinates": [], "width": 1328, "height": 1200, "image_path": "images/1132.png", "bbox_info": [{"box_coordinates": [232, 193, 301, 266], "box_attr": {"box_retain": 1, "box_age": 0}}]}, {"original_image_path": "1133.png", "crop_coordinates": [], "width": 1328, "height": 1200, "image_path": "images/1133.png", "bbox_info": [{"box_coordinates": [230, 216, 310, 276], "box_attr": {"box_retain": 1, "box_age": 0}}]}, {"original_image_path": "1134.png", "crop_coordinates": [], "width": 1328, "height": 1200, "image_path": "images/1134.png", "bbox_info": [{"box_coordinates": [228, 223, 310, 288], "box_attr": {"box_retain": 1, "box_age": 0}}]}, {"original_image_path": "1135.png", "crop_coordinates": [], "width": 1328, "height": 1200, "image_path": "images/1135.png", "bbox_info": [{"box_coordinates": [230, 242, 307, 307], "box_attr": {"box_retain": 1, "box_age": 0}}]}, {"original_image_path": "1136.png", "crop_coordinates": [], "width": 1328, "height": 1200, "image_path": "images/1136.png", "bbox_info": [{"box_coordinates": [232, 272, 309, 334], "box_attr": {"box_retain": 1, "box_age": 0}}]}, {"original_image_path": "1137.png", "crop_coordinates": [], "width": 1328, "height": 1200, "image_path": "images/1137.png", "bbox_info": [{"box_coordinates": [228, 295, 306, 362], "box_attr": {"box_retain": 1, "box_age": 0}}]}, {"original_image_path": "1138.png", "crop_coordinates": [], "width": 1328, "height": 1200, "image_path": "images/1138.png", "bbox_info": [{"box_coordinates": [230, 316, 309, 381], "box_attr": {"box_retain": 1, "box_age": 0}}]}, {"original_image_path": "1139.png", "crop_coordinates": [], "width": 1328, "height": 1200, "image_path": "images/1139.png", "bbox_info": [{"box_coordinates": [233, 332, 312, 403], "box_attr": {"box_retain": 1, "box_age": 0}}]}, {"original_image_path": "1140.png", "crop_coordinates": [], "width": 1328, "height": 1200, "image_path": "images/1140.png", "bbox_info": [{"box_coordinates": [233, 336, 311, 406], "box_attr": {"box_retain": 1, "box_age": 0}}]}, {"original_image_path": "1141.png", "crop_coordinates": [], "width": 1328, "height": 1200, "image_path": "images/1141.png", "bbox_info": [{"box_coordinates": [233, 361, 310, 430], "box_attr": {"box_retain": 1, "box_age": 0}}]}, {"original_image_path": "1142.png", "crop_coordinates": [], "width": 1328, "height": 1200, "image_path": "images/1142.png", "bbox_info": [{"box_coordinates": [230, 403, 309, 471], "box_attr": {"box_retain": 1, "box_age": 0}}, {"box_coordinates": [210, 162, 294, 237], "box_attr": {"box_retain": 1, "box_age": 0}}]}, {"original_image_path": "1143.png", "crop_coordinates": [], "width": 1328, "height": 1200, "image_path": "images/1143.png", "bbox_info": [{"box_coordinates": [230, 406, 307, 478], "box_attr": {"box_retain": 1, "box_age": 0}}, {"box_coordinates": [208, 167, 296, 242], "box_attr": {"box_retain": 1, "box_age": 0}}]}, {"original_image_path": "1144.png", "crop_coordinates": [], "width": 1328, "height": 1200, "image_path": "images/1144.png", "bbox_info": [{"box_coordinates": [209, 181, 292, 254], "box_attr": {"box_retain": 1, "box_age": 0}}, {"box_coordinates": [232, 421, 308, 488], "box_attr": {"box_retain": 1, "box_age": 0}}]}, {"original_image_path": "1145.png", "crop_coordinates": [], "width": 1328, "height": 1200, "image_path": "images/1145.png", "bbox_info": [{"box_coordinates": [210, 203, 295, 277], "box_attr": {"box_retain": 1, "box_age": 0}}]}, {"original_image_path": "1146.png", "crop_coordinates": [], "width": 1328, "height": 1200, "image_path": "images/1146.png", "bbox_info": [{"box_coordinates": [209, 210, 297, 283], "box_attr": {"box_retain": 1, "box_age": 0}}]}, {"original_image_path": "1147.png", "crop_coordinates": [], "width": 1328, "height": 1200, "image_path": "images/1147.png", "bbox_info": [{"box_coordinates": [210, 234, 295, 304], "box_attr": {"box_retain": 1, "box_age": 0}}]}, {"original_image_path": "1148.png", "crop_coordinates": [], "width": 1328, "height": 1200, "image_path": "images/1148.png", "bbox_info": [{"box_coordinates": [209, 257, 298, 327], "box_attr": {"box_retain": 1, "box_age": 0}}]}, {"original_image_path": "1149.png", "crop_coordinates": [], "width": 1328, "height": 1200, "image_path": "images/1149.png", "bbox_info": [{"box_coordinates": [209, 279, 277, 348], "box_attr": {"box_retain": 1, "box_age": 0}}]}, {"original_image_path": "1150.png", "crop_coordinates": [], "width": 1328, "height": 1200, "image_path": "images/1150.png", "bbox_info": [{"box_coordinates": [211, 300, 280, 371], "box_attr": {"box_retain": 1, "box_age": 0}}]}, {"original_image_path": "1151.png", "crop_coordinates": [], "width": 1328, "height": 1200, "image_path": "images/1151.png", "bbox_info": [{"box_coordinates": [209, 324, 281, 393], "box_attr": {"box_retain": 1, "box_age": 0}}]}, {"original_image_path": "1152.png", "crop_coordinates": [], "width": 1328, "height": 1200, "image_path": "images/1152.png", "bbox_info": [{"box_coordinates": [210, 338, 283, 414], "box_attr": {"box_retain": 1, "box_age": 0}}]}, {"original_image_path": "1153.png", "crop_coordinates": [], "width": 1328, "height": 1200, "image_path": "images/1153.png", "bbox_info": [{"box_coordinates": [210, 346, 283, 418], "box_attr": {"box_retain": 1, "box_age": 0}}]}, {"original_image_path": "1154.png", "crop_coordinates": [], "width": 1328, "height": 1200, "image_path": "images/1154.png", "bbox_info": [{"box_coordinates": [212, 366, 283, 437], "box_attr": {"box_retain": 1, "box_age": 0}}]}, {"original_image_path": "1155.png", "crop_coordinates": [], "width": 1328, "height": 1200, "image_path": "images/1155.png", "bbox_info": [{"box_coordinates": [212, 387, 281, 461], "box_attr": {"box_retain": 1, "box_age": 0}}]}, {"original_image_path": "1156.png", "crop_coordinates": [], "width": 1328, "height": 1200, "image_path": "images/1156.png", "bbox_info": [{"box_coordinates": [213, 411, 281, 482], "box_attr": {"box_retain": 1, "box_age": 0}}]}, {"original_image_path": "1166.png", "crop_coordinates": [], "width": 1328, "height": 1200, "image_path": "images/1166.png", "bbox_info": [{"box_coordinates": [212, 165, 287, 240], "box_attr": {"box_retain": 1, "box_age": 0}}]}, {"original_image_path": "1167.png", "crop_coordinates": [], "width": 1328, "height": 1200, "image_path": "images/1167.png", "bbox_info": [{"box_coordinates": [216, 187, 289, 267], "box_attr": {"box_retain": 1, "box_age": 0}}]}, {"original_image_path": "1168.png", "crop_coordinates": [], "width": 1328, "height": 1200, "image_path": "images/1168.png", "bbox_info": [{"box_coordinates": [214, 202, 290, 282], "box_attr": {"box_retain": 1, "box_age": 0}}]}, {"original_image_path": "1169.png", "crop_coordinates": [], "width": 1328, "height": 1200, "image_path": "images/1169.png", "bbox_info": [{"box_coordinates": [216, 225, 293, 303], "box_attr": {"box_retain": 1, "box_age": 0}}]}, {"original_image_path": "1170.png", "crop_coordinates": [], "width": 1328, "height": 1200, "image_path": "images/1170.png", "bbox_info": [{"box_coordinates": [214, 230, 292, 308], "box_attr": {"box_retain": 1, "box_age": 0}}]}, {"original_image_path": "1171.png", "crop_coordinates": [], "width": 1328, "height": 1200, "image_path": "images/1171.png", "bbox_info": [{"box_coordinates": [214, 252, 292, 332], "box_attr": {"box_retain": 1, "box_age": 0}}]}, {"original_image_path": "1172.png", "crop_coordinates": [], "width": 1328, "height": 1200, "image_path": "images/1172.png", "bbox_info": [{"box_coordinates": [214, 274, 292, 354], "box_attr": {"box_retain": 1, "box_age": 0}}]}, {"original_image_path": "1173.png", "crop_coordinates": [], "width": 1328, "height": 1200, "image_path": "images/1173.png", "bbox_info": [{"box_coordinates": [214, 289, 292, 370], "box_attr": {"box_retain": 1, "box_age": 0}}]}, {"original_image_path": "1174.png", "crop_coordinates": [], "width": 1328, "height": 1200, "image_path": "images/1174.png", "bbox_info": [{"box_coordinates": [215, 294, 292, 378], "box_attr": {"box_retain": 1, "box_age": 0}}]}, {"original_image_path": "1175.png", "crop_coordinates": [], "width": 1328, "height": 1200, "image_path": "images/1175.png", "bbox_info": [{"box_coordinates": [214, 315, 294, 399], "box_attr": {"box_retain": 1, "box_age": 0}}]}, {"original_image_path": "1176.png", "crop_coordinates": [], "width": 1328, "height": 1200, "image_path": "images/1176.png", "bbox_info": [{"box_coordinates": [217, 336, 294, 420], "box_attr": {"box_retain": 1, "box_age": 0}}]}, {"original_image_path": "1177.png", "crop_coordinates": [], "width": 1328, "height": 1200, "image_path": "images/1177.png", "bbox_info": [{"box_coordinates": [219, 357, 294, 445], "box_attr": {"box_retain": 1, "box_age": 0}}]}, {"original_image_path": "1178.png", "crop_coordinates": [], "width": 1328, "height": 1200, "image_path": "images/1178.png", "bbox_info": [{"box_coordinates": [216, 382, 293, 464], "box_attr": {"box_retain": 1, "box_age": 0}}]}, {"original_image_path": "1179.png", "crop_coordinates": [], "width": 1328, "height": 1200, "image_path": "images/1179.png", "bbox_info": [{"box_coordinates": [216, 399, 292, 482], "box_attr": {"box_retain": 1, "box_age": 0}}]}, {"original_image_path": "1180.png", "crop_coordinates": [], "width": 1328, "height": 1200, "image_path": "images/1180.png", "bbox_info": [{"box_coordinates": [216, 402, 292, 486], "box_attr": {"box_retain": 1, "box_age": 0}}]}, {"original_image_path": "1182.png", "crop_coordinates": [], "width": 1328, "height": 1200, "image_path": "images/1182.png", "bbox_info": [{"box_coordinates": [230, 184, 317, 269], "box_attr": {"box_retain": 1, "box_age": 0}}]}, {"original_image_path": "1183.png", "crop_coordinates": [], "width": 1328, "height": 1200, "image_path": "images/1183.png", "bbox_info": [{"box_coordinates": [227, 215, 335, 293], "box_attr": {"box_retain": 1, "box_age": 0}}]}, {"original_image_path": "1184.png", "crop_coordinates": [], "width": 1328, "height": 1200, "image_path": "images/1184.png", "bbox_info": [{"box_coordinates": [227, 217, 336, 295], "box_attr": {"box_retain": 1, "box_age": 0}}]}, {"original_image_path": "1185.png", "crop_coordinates": [], "width": 1328, "height": 1200, "image_path": "images/1185.png", "bbox_info": [{"box_coordinates": [229, 233, 331, 315], "box_attr": {"box_retain": 1, "box_age": 0}}]}, {"original_image_path": "1186.png", "crop_coordinates": [], "width": 1328, "height": 1200, "image_path": "images/1186.png", "bbox_info": [{"box_coordinates": [228, 258, 332, 337], "box_attr": {"box_retain": 1, "box_age": 0}}]}, {"original_image_path": "1187.png", "crop_coordinates": [], "width": 1328, "height": 1200, "image_path": "images/1187.png", "bbox_info": [{"box_coordinates": [230, 281, 336, 361], "box_attr": {"box_retain": 1, "box_age": 0}}]}, {"original_image_path": "1188.png", "crop_coordinates": [], "width": 1328, "height": 1200, "image_path": "images/1188.png", "bbox_info": [{"box_coordinates": [227, 301, 333, 382], "box_attr": {"box_retain": 1, "box_age": 0}}]}, {"original_image_path": "1189.png", "crop_coordinates": [], "width": 1328, "height": 1200, "image_path": "images/1189.png", "bbox_info": [{"box_coordinates": [229, 319, 334, 400], "box_attr": {"box_retain": 1, "box_age": 0}}]}, {"original_image_path": "1190.png", "crop_coordinates": [], "width": 1328, "height": 1200, "image_path": "images/1190.png", "bbox_info": [{"box_coordinates": [228, 329, 336, 412], "box_attr": {"box_retain": 1, "box_age": 0}}]}, {"original_image_path": "1191.png", "crop_coordinates": [], "width": 1328, "height": 1200, "image_path": "images/1191.png", "bbox_info": [{"box_coordinates": [212, 157, 270, 219], "box_attr": {"box_retain": 1, "box_age": 0}}, {"box_coordinates": [227, 350, 334, 430], "box_attr": {"box_retain": 1, "box_age": 0}}]}, {"original_image_path": "1192.png", "crop_coordinates": [], "width": 1328, "height": 1200, "image_path": "images/1192.png", "bbox_info": [{"box_coordinates": [216, 183, 269, 240], "box_attr": {"box_retain": 1, "box_age": 0}}, {"box_coordinates": [230, 372, 335, 458], "box_attr": {"box_retain": 1, "box_age": 0}}]}, {"original_image_path": "1193.png", "crop_coordinates": [], "width": 1328, "height": 1200, "image_path": "images/1193.png", "bbox_info": [{"box_coordinates": [212, 196, 267, 256], "box_attr": {"box_retain": 1, "box_age": 0}}, {"box_coordinates": [229, 393, 336, 473], "box_attr": {"box_retain": 1, "box_age": 0}}]}, {"original_image_path": "1194.png", "crop_coordinates": [], "width": 1328, "height": 1200, "image_path": "images/1194.png", "bbox_info": [{"box_coordinates": [209, 228, 267, 283], "box_attr": {"box_retain": 1, "box_age": 0}}]}, {"original_image_path": "1195.png", "crop_coordinates": [], "width": 1328, "height": 1200, "image_path": "images/1195.png", "bbox_info": [{"box_coordinates": [212, 246, 269, 304], "box_attr": {"box_retain": 1, "box_age": 0}}]}, {"original_image_path": "1196.png", "crop_coordinates": [], "width": 1328, "height": 1200, "image_path": "images/1196.png", "bbox_info": [{"box_coordinates": [212, 264, 269, 320], "box_attr": {"box_retain": 1, "box_age": 0}}]}, {"original_image_path": "1197.png", "crop_coordinates": [], "width": 1328, "height": 1200, "image_path": "images/1197.png", "bbox_info": [{"box_coordinates": [210, 270, 270, 328], "box_attr": {"box_retain": 1, "box_age": 0}}]}, {"original_image_path": "1198.png", "crop_coordinates": [], "width": 1328, "height": 1200, "image_path": "images/1198.png", "bbox_info": [{"box_coordinates": [210, 294, 268, 351], "box_attr": {"box_retain": 1, "box_age": 0}}]}, {"original_image_path": "1199.png", "crop_coordinates": [], "width": 1328, "height": 1200, "image_path": "images/1199.png", "bbox_info": [{"box_coordinates": [211, 320, 270, 378], "box_attr": {"box_retain": 1, "box_age": 0}}]}, {"original_image_path": "1200.png", "crop_coordinates": [], "width": 1328, "height": 1200, "image_path": "images/1200.png", "bbox_info": [{"box_coordinates": [214, 342, 269, 399], "box_attr": {"box_retain": 1, "box_age": 0}}]}, {"original_image_path": "1201.png", "crop_coordinates": [], "width": 1328, "height": 1200, "image_path": "images/1201.png", "bbox_info": [{"box_coordinates": [212, 357, 270, 412], "box_attr": {"box_retain": 1, "box_age": 0}}]}, {"original_image_path": "1202.png", "crop_coordinates": [], "width": 1328, "height": 1200, "image_path": "images/1202.png", "bbox_info": [{"box_coordinates": [215, 362, 270, 416], "box_attr": {"box_retain": 1, "box_age": 0}}]}, {"original_image_path": "1203.png", "crop_coordinates": [], "width": 1328, "height": 1200, "image_path": "images/1203.png", "bbox_info": [{"box_coordinates": [212, 384, 270, 443], "box_attr": {"box_retain": 1, "box_age": 0}}]}, {"original_image_path": "1204.png", "crop_coordinates": [], "width": 1328, "height": 1200, "image_path": "images/1204.png", "bbox_info": [{"box_coordinates": [214, 409, 271, 464], "box_attr": {"box_retain": 1, "box_age": 0}}]}, {"original_image_path": "1205.png", "crop_coordinates": [], "width": 1328, "height": 1200, "image_path": "images/1205.png", "bbox_info": [{"box_coordinates": [216, 433, 270, 487], "box_attr": {"box_retain": 1, "box_age": 0}}]}, {"original_image_path": "1207.png", "crop_coordinates": [], "width": 1328, "height": 1200, "image_path": "images/1207.png", "bbox_info": [{"box_coordinates": [152, 172, 283, 274], "box_attr": {"box_retain": 1, "box_age": 0}}]}, {"original_image_path": "1208.png", "crop_coordinates": [], "width": 1328, "height": 1200, "image_path": "images/1208.png", "bbox_info": [{"box_coordinates": [146, 186, 283, 294], "box_attr": {"box_retain": 1, "box_age": 0}}]}, {"original_image_path": "1209.png", "crop_coordinates": [], "width": 1328, "height": 1200, "image_path": "images/1209.png", "bbox_info": [{"box_coordinates": [149, 192, 282, 302], "box_attr": {"box_retain": 1, "box_age": 0}}]}, {"original_image_path": "1210.png", "crop_coordinates": [], "width": 1328, "height": 1200, "image_path": "images/1210.png", "bbox_info": [{"box_coordinates": [154, 223, 284, 329], "box_attr": {"box_retain": 1, "box_age": 0}}]}, {"original_image_path": "1211.png", "crop_coordinates": [], "width": 1328, "height": 1200, "image_path": "images/1211.png", "bbox_info": [{"box_coordinates": [149, 247, 284, 350], "box_attr": {"box_retain": 1, "box_age": 0}}]}, {"original_image_path": "1212.png", "crop_coordinates": [], "width": 1328, "height": 1200, "image_path": "images/1212.png", "bbox_info": [{"box_coordinates": [147, 270, 284, 366], "box_attr": {"box_retain": 1, "box_age": 0}}]}, {"original_image_path": "1213.png", "crop_coordinates": [], "width": 1328, "height": 1200, "image_path": "images/1213.png", "bbox_info": [{"box_coordinates": [149, 290, 283, 384], "box_attr": {"box_retain": 1, "box_age": 0}}]}, {"original_image_path": "1214.png", "crop_coordinates": [], "width": 1328, "height": 1200, "image_path": "images/1214.png", "bbox_info": [{"box_coordinates": [152, 315, 283, 402], "box_attr": {"box_retain": 1, "box_age": 0}}]}, {"original_image_path": "1215.png", "crop_coordinates": [], "width": 1328, "height": 1200, "image_path": "images/1215.png", "bbox_info": [{"box_coordinates": [149, 319, 282, 415], "box_attr": {"box_retain": 1, "box_age": 0}}]}, {"original_image_path": "1216.png", "crop_coordinates": [], "width": 1328, "height": 1200, "image_path": "images/1216.png", "bbox_info": [{"box_coordinates": [150, 341, 282, 439], "box_attr": {"box_retain": 1, "box_age": 0}}, {"box_coordinates": [191, 179, 272, 239], "box_attr": {"box_retain": 1, "box_age": 0}}]}, {"original_image_path": "1217.png", "crop_coordinates": [], "width": 1328, "height": 1200, "image_path": "images/1217.png", "bbox_info": [{"box_coordinates": [199, 188, 276, 256], "box_attr": {"box_retain": 1, "box_age": 0}}, {"box_coordinates": [153, 369, 281, 461], "box_attr": {"box_retain": 1, "box_age": 0}}]}, {"original_image_path": "1218.png", "crop_coordinates": [], "width": 1328, "height": 1200, "image_path": "images/1218.png", "bbox_info": [{"box_coordinates": [198, 215, 270, 276], "box_attr": {"box_retain": 1, "box_age": 0}}, {"box_coordinates": [150, 387, 282, 484], "box_attr": {"box_retain": 1, "box_age": 0}}]}, {"original_image_path": "1219.png", "crop_coordinates": [], "width": 1328, "height": 1200, "image_path": "images/1219.png", "bbox_info": [{"box_coordinates": [192, 238, 269, 295], "box_attr": {"box_retain": 1, "box_age": 0}}]}, {"original_image_path": "1220.png", "crop_coordinates": [], "width": 1328, "height": 1200, "image_path": "images/1220.png", "bbox_info": [{"box_coordinates": [194, 242, 269, 301], "box_attr": {"box_retain": 1, "box_age": 0}}]}, {"original_image_path": "1221.png", "crop_coordinates": [], "width": 1328, "height": 1200, "image_path": "images/1221.png", "bbox_info": [{"box_coordinates": [196, 258, 267, 320], "box_attr": {"box_retain": 1, "box_age": 0}}]}, {"original_image_path": "1222.png", "crop_coordinates": [], "width": 1328, "height": 1200, "image_path": "images/1222.png", "bbox_info": [{"box_coordinates": [192, 283, 270, 346], "box_attr": {"box_retain": 1, "box_age": 0}}]}, {"original_image_path": "1223.png", "crop_coordinates": [], "width": 1328, "height": 1200, "image_path": "images/1223.png", "bbox_info": [{"box_coordinates": [192, 304, 270, 365], "box_attr": {"box_retain": 1, "box_age": 0}}]}, {"original_image_path": "1224.png", "crop_coordinates": [], "width": 1328, "height": 1200, "image_path": "images/1224.png", "bbox_info": [{"box_coordinates": [194, 321, 271, 384], "box_attr": {"box_retain": 1, "box_age": 0}}]}, {"original_image_path": "1225.png", "crop_coordinates": [], "width": 1328, "height": 1200, "image_path": "images/1225.png", "bbox_info": [{"box_coordinates": [192, 327, 269, 389], "box_attr": {"box_retain": 1, "box_age": 0}}]}, {"original_image_path": "1226.png", "crop_coordinates": [], "width": 1328, "height": 1200, "image_path": "images/1226.png", "bbox_info": [{"box_coordinates": [191, 355, 270, 408], "box_attr": {"box_retain": 1, "box_age": 0}}]}, {"original_image_path": "1227.png", "crop_coordinates": [], "width": 1328, "height": 1200, "image_path": "images/1227.png", "bbox_info": [{"box_coordinates": [191, 374, 270, 435], "box_attr": {"box_retain": 1, "box_age": 0}}]}, {"original_image_path": "1228.png", "crop_coordinates": [], "width": 1328, "height": 1200, "image_path": "images/1228.png", "bbox_info": [{"box_coordinates": [194, 393, 269, 452], "box_attr": {"box_retain": 1, "box_age": 0}}]}, {"original_image_path": "1229.png", "crop_coordinates": [], "width": 1328, "height": 1200, "image_path": "images/1229.png", "bbox_info": [{"box_coordinates": [194, 418, 267, 473], "box_attr": {"box_retain": 1, "box_age": 0}}, {"box_coordinates": [196, 144, 275, 232], "box_attr": {"box_retain": 1, "box_age": 0}}]}, {"original_image_path": "1230.png", "crop_coordinates": [], "width": 1328, "height": 1200, "image_path": "images/1230.png", "bbox_info": [{"box_coordinates": [192, 167, 281, 238], "box_attr": {"box_retain": 1, "box_age": 0}}]}, {"original_image_path": "1231.png", "crop_coordinates": [], "width": 1328, "height": 1200, "image_path": "images/1231.png", "bbox_info": [{"box_coordinates": [190, 188, 281, 269], "box_attr": {"box_retain": 1, "box_age": 0}}]}, {"original_image_path": "1232.png", "crop_coordinates": [], "width": 1328, "height": 1200, "image_path": "images/1232.png", "bbox_info": [{"box_coordinates": [193, 204, 278, 284], "box_attr": {"box_retain": 1, "box_age": 0}}]}, {"original_image_path": "1233.png", "crop_coordinates": [], "width": 1328, "height": 1200, "image_path": "images/1233.png", "bbox_info": [{"box_coordinates": [192, 208, 280, 295], "box_attr": {"box_retain": 1, "box_age": 0}}]}, {"original_image_path": "1234.png", "crop_coordinates": [], "width": 1328, "height": 1200, "image_path": "images/1234.png", "bbox_info": [{"box_coordinates": [189, 231, 278, 306], "box_attr": {"box_retain": 1, "box_age": 0}}]}, {"original_image_path": "1235.png", "crop_coordinates": [], "width": 1328, "height": 1200, "image_path": "images/1235.png", "bbox_info": [{"box_coordinates": [189, 253, 276, 333], "box_attr": {"box_retain": 1, "box_age": 0}}]}, {"original_image_path": "1236.png", "crop_coordinates": [], "width": 1328, "height": 1200, "image_path": "images/1236.png", "bbox_info": [{"box_coordinates": [186, 267, 276, 350], "box_attr": {"box_retain": 1, "box_age": 0}}]}, {"original_image_path": "1237.png", "crop_coordinates": [], "width": 1328, "height": 1200, "image_path": "images/1237.png", "bbox_info": [{"box_coordinates": [189, 295, 278, 374], "box_attr": {"box_retain": 1, "box_age": 0}}]}, {"original_image_path": "1238.png", "crop_coordinates": [], "width": 1328, "height": 1200, "image_path": "images/1238.png", "bbox_info": [{"box_coordinates": [189, 312, 278, 394], "box_attr": {"box_retain": 1, "box_age": 0}}]}, {"original_image_path": "1239.png", "crop_coordinates": [], "width": 1328, "height": 1200, "image_path": "images/1239.png", "bbox_info": [{"box_coordinates": [191, 316, 278, 399], "box_attr": {"box_retain": 1, "box_age": 0}}]}, {"original_image_path": "1240.png", "crop_coordinates": [], "width": 1328, "height": 1200, "image_path": "images/1240.png", "bbox_info": [{"box_coordinates": [189, 338, 278, 422], "box_attr": {"box_retain": 1, "box_age": 0}}]}, {"original_image_path": "1241.png", "crop_coordinates": [], "width": 1328, "height": 1200, "image_path": "images/1241.png", "bbox_info": [{"box_coordinates": [189, 369, 275, 448], "box_attr": {"box_retain": 1, "box_age": 0}}]}, {"original_image_path": "1242.png", "crop_coordinates": [], "width": 1328, "height": 1200, "image_path": "images/1242.png", "bbox_info": [{"box_coordinates": [189, 385, 278, 467], "box_attr": {"box_retain": 1, "box_age": 0}}]}, {"original_image_path": "1243.png", "crop_coordinates": [], "width": 1328, "height": 1200, "image_path": "images/1243.png", "bbox_info": [{"box_coordinates": [189, 392, 278, 475], "box_attr": {"box_retain": 1, "box_age": 0}}]}, {"original_image_path": "1258.png", "crop_coordinates": [], "width": 1328, "height": 1200, "image_path": "images/1258.png", "bbox_info": [{"box_coordinates": [160, 203, 289, 301], "box_attr": {"box_retain": 1, "box_age": 0}}]}, {"original_image_path": "1259.png", "crop_coordinates": [], "width": 1328, "height": 1200, "image_path": "images/1259.png", "bbox_info": [{"box_coordinates": [161, 227, 290, 330], "box_attr": {"box_retain": 1, "box_age": 0}}]}, {"original_image_path": "1260.png", "crop_coordinates": [], "width": 1328, "height": 1200, "image_path": "images/1260.png", "bbox_info": [{"box_coordinates": [164, 246, 294, 354], "box_attr": {"box_retain": 1, "box_age": 0}}]}, {"original_image_path": "1261.png", "crop_coordinates": [], "width": 1328, "height": 1200, "image_path": "images/1261.png", "bbox_info": [{"box_coordinates": [163, 252, 294, 357], "box_attr": {"box_retain": 1, "box_age": 0}}]}, {"original_image_path": "1262.png", "crop_coordinates": [], "width": 1328, "height": 1200, "image_path": "images/1262.png", "bbox_info": [{"box_coordinates": [167, 275, 292, 380], "box_attr": {"box_retain": 1, "box_age": 0}}]}, {"original_image_path": "1263.png", "crop_coordinates": [], "width": 1328, "height": 1200, "image_path": "images/1263.png", "bbox_info": [{"box_coordinates": [165, 296, 294, 408], "box_attr": {"box_retain": 1, "box_age": 0}}]}, {"original_image_path": "1264.png", "crop_coordinates": [], "width": 1328, "height": 1200, "image_path": "images/1264.png", "bbox_info": [{"box_coordinates": [164, 322, 290, 432], "box_attr": {"box_retain": 1, "box_age": 0}}]}, {"original_image_path": "1265.png", "crop_coordinates": [], "width": 1328, "height": 1200, "image_path": "images/1265.png", "bbox_info": [{"box_coordinates": [163, 341, 290, 452], "box_attr": {"box_retain": 1, "box_age": 0}}]}, {"original_image_path": "1266.png", "crop_coordinates": [], "width": 1328, "height": 1200, "image_path": "images/1266.png", "bbox_info": [{"box_coordinates": [164, 346, 291, 459], "box_attr": {"box_retain": 1, "box_age": 0}}]}, {"original_image_path": "1267.png", "crop_coordinates": [], "width": 1328, "height": 1200, "image_path": "images/1267.png", "bbox_info": [{"box_coordinates": [165, 371, 296, 486], "box_attr": {"box_retain": 1, "box_age": 0}}]}, {"original_image_path": "1268.png", "crop_coordinates": [], "width": 1328, "height": 1200, "image_path": "images/1268.png", "bbox_info": [{"box_coordinates": [155, 150, 290, 268], "box_attr": {"box_retain": 1, "box_age": 0}}]}, {"original_image_path": "1269.png", "crop_coordinates": [], "width": 1328, "height": 1200, "image_path": "images/1269.png", "bbox_info": [{"box_coordinates": [152, 172, 281, 292], "box_attr": {"box_retain": 1, "box_age": 0}}]}, {"original_image_path": "1270.png", "crop_coordinates": [], "width": 1328, "height": 1200, "image_path": "images/1270.png", "bbox_info": [{"box_coordinates": [157, 201, 285, 323], "box_attr": {"box_retain": 1, "box_age": 0}}]}, {"original_image_path": "1271.png", "crop_coordinates": [], "width": 1328, "height": 1200, "image_path": "images/1271.png", "bbox_info": [{"box_coordinates": [153, 220, 284, 337], "box_attr": {"box_retain": 1, "box_age": 0}}]}, {"original_image_path": "1272.png", "crop_coordinates": [], "width": 1328, "height": 1200, "image_path": "images/1272.png", "bbox_info": [{"box_coordinates": [156, 223, 283, 347], "box_attr": {"box_retain": 1, "box_age": 0}}]}, {"original_image_path": "1273.png", "crop_coordinates": [], "width": 1328, "height": 1200, "image_path": "images/1273.png", "bbox_info": [{"box_coordinates": [157, 246, 283, 357], "box_attr": {"box_retain": 0, "box_age": 0}}, {"box_coordinates": [158, 244, 285, 362], "box_attr": {"box_retain": 1, "box_age": 0}}]}, {"original_image_path": "1274.png", "crop_coordinates": [], "width": 1328, "height": 1200, "image_path": "images/1274.png", "bbox_info": [{"box_coordinates": [156, 275, 283, 391], "box_attr": {"box_retain": 1, "box_age": 0}}]}, {"original_image_path": "1275.png", "crop_coordinates": [], "width": 1328, "height": 1200, "image_path": "images/1275.png", "bbox_info": [{"box_coordinates": [157, 298, 281, 413], "box_attr": {"box_retain": 1, "box_age": 0}}]}, {"original_image_path": "1276.png", "crop_coordinates": [], "width": 1328, "height": 1200, "image_path": "images/1276.png", "bbox_info": [{"box_coordinates": [157, 325, 285, 437], "box_attr": {"box_retain": 1, "box_age": 0}}]}, {"original_image_path": "1277.png", "crop_coordinates": [], "width": 1328, "height": 1200, "image_path": "images/1277.png", "bbox_info": [{"box_coordinates": [157, 350, 283, 465], "box_attr": {"box_retain": 1, "box_age": 0}}]}, {"original_image_path": "1278.png", "crop_coordinates": [], "width": 1328, "height": 1200, "image_path": "images/1278.png", "bbox_info": [{"box_coordinates": [154, 377, 283, 484], "box_attr": {"box_retain": 1, "box_age": 0}}]}, {"original_image_path": "1279.png", "crop_coordinates": [], "width": 1328, "height": 1200, "image_path": "images/1279.png", "bbox_info": [{"box_coordinates": [158, 378, 283, 486], "box_attr": {"box_retain": 1, "box_age": 0}}]}, {"original_image_path": "1282.png", "crop_coordinates": [], "width": 1328, "height": 1200, "image_path": "images/1282.png", "bbox_info": [{"box_coordinates": [109, 187, 258, 310], "box_attr": {"box_retain": 1, "box_age": 0}}]}, {"original_image_path": "1283.png", "crop_coordinates": [], "width": 1328, "height": 1200, "image_path": "images/1283.png", "bbox_info": [{"box_coordinates": [127, 212, 265, 337], "box_attr": {"box_retain": 1, "box_age": 0}}]}, {"original_image_path": "1284.png", "crop_coordinates": [], "width": 1328, "height": 1200, "image_path": "images/1284.png", "bbox_info": [{"box_coordinates": [126, 208, 268, 340], "box_attr": {"box_retain": 1, "box_age": 0}}]}, {"original_image_path": "1285.png", "crop_coordinates": [], "width": 1328, "height": 1200, "image_path": "images/1285.png", "bbox_info": [{"box_coordinates": [104, 240, 256, 352], "box_attr": {"box_retain": 1, "box_age": 0}}]}, {"original_image_path": "1286.png", "crop_coordinates": [], "width": 1328, "height": 1200, "image_path": "images/1286.png", "bbox_info": [{"box_coordinates": [102, 267, 245, 381], "box_attr": {"box_retain": 1, "box_age": 0}}]}, {"original_image_path": "1287.png", "crop_coordinates": [], "width": 1328, "height": 1200, "image_path": "images/1287.png", "bbox_info": [{"box_coordinates": [116, 288, 267, 417], "box_attr": {"box_retain": 1, "box_age": 0}}]}, {"original_image_path": "1288.png", "crop_coordinates": [], "width": 1328, "height": 1200, "image_path": "images/1288.png", "bbox_info": [{"box_coordinates": [111, 326, 259, 441], "box_attr": {"box_retain": 1, "box_age": 0}}]}, {"original_image_path": "1289.png", "crop_coordinates": [], "width": 1328, "height": 1200, "image_path": "images/1289.png", "bbox_info": [{"box_coordinates": [101, 344, 251, 462], "box_attr": {"box_retain": 1, "box_age": 0}}, {"box_coordinates": [165, 161, 220, 221], "box_attr": {"box_retain": 1, "box_age": 0}}]}, {"original_image_path": "1290.png", "crop_coordinates": [], "width": 1328, "height": 1200, "image_path": "images/1290.png", "bbox_info": [{"box_coordinates": [112, 363, 258, 482], "box_attr": {"box_retain": 1, "box_age": 0}}, {"box_coordinates": [164, 177, 218, 233], "box_attr": {"box_retain": 1, "box_age": 0}}]}, {"original_image_path": "1291.png", "crop_coordinates": [], "width": 1328, "height": 1200, "image_path": "images/1291.png", "bbox_info": [{"box_coordinates": [114, 369, 261, 488], "box_attr": {"box_retain": 1, "box_age": 0}}, {"box_coordinates": [164, 180, 220, 242], "box_attr": {"box_retain": 1, "box_age": 0}}]}, {"original_image_path": "1292.png", "crop_coordinates": [], "width": 1328, "height": 1200, "image_path": "images/1292.png", "bbox_info": [{"box_coordinates": [163, 201, 219, 259], "box_attr": {"box_retain": 1, "box_age": 0}}]}, {"original_image_path": "1293.png", "crop_coordinates": [], "width": 1328, "height": 1200, "image_path": "images/1293.png", "bbox_info": [{"box_coordinates": [163, 223, 221, 284], "box_attr": {"box_retain": 1, "box_age": 0}}]}, {"original_image_path": "1294.png", "crop_coordinates": [], "width": 1328, "height": 1200, "image_path": "images/1294.png", "bbox_info": [{"box_coordinates": [163, 240, 221, 298], "box_attr": {"box_retain": 1, "box_age": 0}}]}, {"original_image_path": "1295.png", "crop_coordinates": [], "width": 1328, "height": 1200, "image_path": "images/1295.png", "bbox_info": [{"box_coordinates": [163, 246, 223, 306], "box_attr": {"box_retain": 1, "box_age": 0}}]}, {"original_image_path": "1296.png", "crop_coordinates": [], "width": 1328, "height": 1200, "image_path": "images/1296.png", "bbox_info": [{"box_coordinates": [163, 267, 221, 326], "box_attr": {"box_retain": 1, "box_age": 0}}]}, {"original_image_path": "1297.png", "crop_coordinates": [], "width": 1328, "height": 1200, "image_path": "images/1297.png", "bbox_info": [{"box_coordinates": [162, 287, 222, 349], "box_attr": {"box_retain": 1, "box_age": 0}}]}, {"original_image_path": "1298.png", "crop_coordinates": [], "width": 1328, "height": 1200, "image_path": "images/1298.png", "bbox_info": [{"box_coordinates": [162, 320, 221, 375], "box_attr": {"box_retain": 1, "box_age": 0}}]}, {"original_image_path": "1299.png", "crop_coordinates": [], "width": 1328, "height": 1200, "image_path": "images/1299.png", "bbox_info": [{"box_coordinates": [161, 336, 221, 388], "box_attr": {"box_retain": 1, "box_age": 0}}]}, {"original_image_path": "1300.png", "crop_coordinates": [], "width": 1328, "height": 1200, "image_path": "images/1300.png", "bbox_info": [{"box_coordinates": [162, 340, 221, 393], "box_attr": {"box_retain": 1, "box_age": 0}}]}, {"original_image_path": "1301.png", "crop_coordinates": [], "width": 1328, "height": 1200, "image_path": "images/1301.png", "bbox_info": [{"box_coordinates": [165, 363, 221, 416], "box_attr": {"box_retain": 1, "box_age": 0}}]}, {"original_image_path": "1302.png", "crop_coordinates": [], "width": 1328, "height": 1200, "image_path": "images/1302.png", "bbox_info": [{"box_coordinates": [163, 393, 222, 443], "box_attr": {"box_retain": 1, "box_age": 0}}]}, {"original_image_path": "1303.png", "crop_coordinates": [], "width": 1328, "height": 1200, "image_path": "images/1303.png", "bbox_info": [{"box_coordinates": [167, 407, 222, 459], "box_attr": {"box_retain": 1, "box_age": 0}}]}, {"original_image_path": "1304.png", "crop_coordinates": [], "width": 1328, "height": 1200, "image_path": "images/1304.png", "bbox_info": [{"box_coordinates": [168, 412, 223, 465], "box_attr": {"box_retain": 1, "box_age": 0}}]}], "details": {"completion_date": "", "remarks": "", "project_name": "depth_cam_testing", "created_by": "Sushanth", "assigned_to": "", "reviewed_by": "", "num_images": 600, "status": "annotation", "creation_date": "29-03-2022", "state": "karnataka", "location": "ts-farm", "date_of_capture": "08-23-2019", "age_group": "41-50", "time_of_capture": "2 PM - 4 PM", "lighting": "Bright", "weed_density": "Low", "soil_type": "Dry", "age_of_crop": 42, "crop": "cotton", "disease_severity": "High", "base_url": "", "parent_folder": "", "camera_angle": ""}, "Age Details": {"1": "broad_leaf", "2": "narrow_leaf", "3": "heart_shaped", "4": "miscellaneous"}}